pop_build/conf.py
pop_build/scripts.py
pop_build/version.py
pop_build/pop_build/build.py
pop_build/pop_build/data.py
pop_build/pop_build/init.py
pop_build/pop_build/inst.py
pop_build/pop_build/post.py
pop_build/pop_build/venv.py
pop_build/pop_build/pkg/fpm.py
pop_build/pop_build/pkg/init.py
pop_build/pop_build/pkg/msi.py
pop_build-3.7.dist-info/LICENSE
pop_build-3.7.dist-info/METADATA
pop_build-3.7.dist-info/WHEEL
pop_build-3.7.dist-info/entry_points.txt
pop_build-3.7.dist-info/top_level.txt
pop_build-3.7.dist-info/RECORD
