Metadata-Version: 2.1
Name: pop-build
Version: 3.7
Summary: Pop's build system, used to build python projects
Home-page: http://github/saltstack/pop-build
Author: Thomas S Hatch
Author-email: thatch@saltstack.com
License: UNKNOWN
Platform: UNKNOWN
Classifier: Operating System :: OS Independent
Classifier: Programming Language :: Python
Classifier: Programming Language :: Python :: 3.6
Classifier: Programming Language :: Python :: 3.7
Classifier: Programming Language :: Python :: 3.8
Classifier: Development Status :: 5 - Production/Stable
Requires-Python: >=3.6
Requires-Dist: pop (>=10.1)
